<street>
<head>Banner street,</head><head2><i>St. Luke's</i> (<b>E.C.</b>), 80 <i>Bunhill row to</i> 130 <i>Up. Whitecross street</i>.</head2>
<map>MAP N7, N8.</map>
<addr>2 &amp; 3 <i>Houseless Poor Asylum</i>, B. Radford, sec Mrs. Jane King, matron</addr>
<addr>5 Rumball Samuel Hy. undertaker</addr>
<addr>6 &amp; 7 Smith Geo. F. fancy box ma</addr>
<addr>8 Soully Richard,moulding mnfctr</addr>
<addr>9 ParrottWm.&amp;Sons,cardboardma</addr>
<addr>12 Phillips Charles, brass founder</addr>
<addr>13 Hore William, tin plate worker</addr>
<addr>19 Goodchild SI. H. color manfactr</addr>
<addr>21 McBride Jas. horse hair mat ma</addr>
<addr>22 Elder Charles, gold beater
Kaufmann Adolph, tailor</addr>
<addr>23 Roberts George, furrier</addr>
<addr>24 Johnson Geo. shirt collar dresser</addr>
<addr>26 Tasker &amp; Lee, shirt dressers</addr>
<addr>28 Briscoe Josiah &amp; Co. printers</addr>
<addr>29 MaxwellJsph. &amp; Son, brassfoundr</addr>
<addr>30 Sabberton William, fancy box ma</addr>
<addr>31 Heard J. G. &amp; Co. who. stationers</addr>
<addr>31 Pigram &amp; Co. engineers</addr>
<addr>33 Haskins George White, revolving shutter maker</addr>
<addr>38 Gilchrist Charles, lindraper</addr>
<addr>41 Smith Walter, butcher</addr>
<xst>here is Coleman street</xst>
<addr>43 Collett John, hair dresser</addr>
<addr>44 Humming Chas. boot &amp; shoe ma</addr>
<addr>47 Browne Mrs. Elizabeth Sarah, chandler's shop</addr>
<addr>49 Long Wm. cabinet brass finisher</addr>
<addr>50 Byne Henry, tinman</addr>
<addr>51 &amp; 52 <i>Prince of Wales</i>, Chas. Pay</addr>
<addr>54 Norton James, gold beater</addr>
<addr>57 Hague John, cutler</addr>
<addr>62 Turpin Brothers, watchmakers</addr>
<addr>63 <i>Hope</i>, Robert Dean</addr>
<addr>64 Thomson Robert, wood carver</addr>
<addr>Heath Walter John, turncock</addr>
<addr>Brown Joseph, printer</addr>
<addr>67 Dring Fredk.Wm. chandlr.'s shp</addr>
<addr>68 JonesEdmd.C.widows' cap makr</addr>
<addr>69 SpeerHy. Jas. &amp;Sons, ivory turnrs</addr>
<addr>72 <i>Public Vaccination Station</i>, EdgarG.Pottle, M.D.med. officr</addr>
<addr>73 Bland Mrs. Mary, coffee rooms</addr>
<addr>Johnson Thomas, appraiser</addr>
</street>
