<street>
<head>Blount st.,</head><head2><i>Limehouse fields</i> (<b>E.</b>), <i>from</i> 97 <i>Salmon's lane to</i> 86 <i>Maroon st</i>.</head2><map>MAP S9.</map>
<addr>2 Rozzell Wm.O. P. wood engraver</addr>
<addr>6 Jackson Edwin, house decorator</addr>
<addr>8 Conway Alfred, edge tool maker</addr>
<addr>16 &amp; 28 Gill William, ship's hearth maker &amp; sawing mills</addr>
<addr>30 Marahall Thos. chandler's shop</addr>
<addr>21 Heiser Henry George, builder</addr>
<addr>31 Bignell Edwin, beer retailer</addr>
<addr>55 Hall Alfred, chandler's shop</addr>
</street>
