<street>
<head>Borough road,</head><head2><i>Southwark</i> (<b>S.E.</b>), <i>commencing at the Obelisk, Blackfriars road</i>.</head2>
<map>MAP M11, N11.</map>
<addr>1 Foakes Mrs. Matilda, fruiterer</addr>
<addr>2 Smith John, hairdresser</addr>
<addr>5 Ball Herbert Cannon, tailor</addr>
<addr>6 Chambers Geo. packing case ma</addr>
<xst>here is New street</xst>
<addr>6A, Anstey Alfred, linendraper</addr>
<addr>7 Howe Robert, coach broker</addr>
<addr>8 Ponder George,perambulator ma</addr>
<addr>9 Harris Edwin, chair maker</addr>
<addr>10 Parry Benj.children's shoemaker</addr>
<addr>11 Heather Thomas, bottle wareho</addr>
<addr>12 Davis Mrs.Sarah,furniture brokr</addr>
<addr>13 &amp; 14 Jennings Joseph, file cutter</addr>
<addr>15 Knight Edward Wm.beer retailer</addr>
<addr>16 Lawrence John, baker</addr>
<xst>here is Warwick street</xst>
<addr>17 BurfleldThs.Geo.pat. axletree ma</addr>
<addr>Henderson Mrs. M.chandler's shp</addr>
<addr>18 Wilson William, tobacconist</addr>
<addr>19 Gould Edward, grocer</addr>
<addr>20 Pain Frederick, oilman</addr>
<addr>21 Page Wm. &amp; Thos, pawnbrokers</addr>
<addr>BOROUGH ROAD CONGREGATIONAL CHAPEL</addr>
<addr>22 Williams Mrs. Harriet, grocer</addr>
<addr>23 Garrett Mrs. Jane, baker</addr>
<addr>24 WillcoxThos.coach&amp;wheel brokr</addr>
<addr>25 Miller WilliamHen.printseller&amp;c</addr>
<addr>26 Hicks George, butcher</addr>
<addr>27 &amp; 28 Mitchell John, coach broker</addr>
<addr>29 Knowles Robert A. scalemaker</addr>
<addr>30 <i>Bridge House</i>, William Edwards</addr>
<xst>here is Lancaster street</xst>
<addr>31 &amp; 32 Boswell Ptr.coach ironmngr</addr>
<addr>33, 34&amp;102 Biggs John,gas engineer</addr>
<addr>35 Mackintosh George, wheel wright
36A, Michelmore &amp; Reap, hinge manufacturers</addr>
<addr>37 Lansdale James, coal sack makr</addr>
<addr>38 Smith John Martin, cleansing powder manufacturer</addr>
<addr>39 Bishopp Harry G. tobacco manfr</addr>
<addr>40 Wake&amp;Dean, school slate makers</addr>
<addr>41 Belleini Francis Wm.shirt dresser</addr>
<addr>42 Jones &amp; Firmin, sign writers</addr>
<addr>43 Davis Charles, tin plate worker</addr>
<xst>here is Belvedere place</xst>
<addr>Humphreys James C. iron mer</addr>
<addr>44 Eglington James,carriage dealer</addr>
<addr>45 Robinson James, coffee rooms</addr>
<addr>46 Rouse Mark, linen draper</addr>
<addr>LONDON, CHATHAM &amp; DOVER RAILWAY STATION</addr>
<xst>here is Southwark bridge road</xst>
<addr>47 <i>Duke of York</i>, William Ledger</addr>
<addr>48 Holt Charles, confectioner</addr>
<addr>50 White John Richard, undertaker</addr>
<addr>52, 55 &amp;56Dobson.Hy.Thos.wire wkr</addr>
<addr>53 Burley William Henry, engineer</addr>
<addr>54 Store Robert, tailor</addr>
<addr>57 James Thomas, chair &amp; sofa ma</addr>
<addr>58 Green John, builder</addr>
<addr>59 Hatch Hy. Edmund, loan office</addr>
<addr>60 Passmore Francis, printer</addr>
<addr>63 &amp; 64 BeeversMrs.E.&amp;Hy.masons</addr>
<addr>65 Love John, beer retailer</addr>
<xst>here is Montague street</xst>
<addr>66 Shaw Brothers, printers</addr>
<addr>67 Hart Walter, surgeon</addr>
<addr>68 <i>Ship</i>, Isaac Brittain</addr>
<xst>here is Blackman street</xst>
<addr>69 Ratcliff Thos. Skeen, tobacconist</addr>
<addr>70 Burrows George, hairdresser</addr>
<addr>71 Dornan Edward, hatter</addr>
<addr>72 Scates Edward, tailor</addr>
<addr>73 &amp; 74 Lillywhite (James), Frowd &amp; Co. cricket outfitters</addr>
<addr>74 Rentmore William, builder</addr>
<addr>75 Quarterman Wm.Hy.coffee rooms</addr>
<addr>76 Holt, Sinden &amp; Co. wholesale bedstead makers</addr>
<addr>80 Robinson (Crescens) &amp; Co. Atlas paper works</addr>
<addr>81 <i>St. George the Martyr Vestry Hall</i>, Alexander Millar, vestry clerk</addr>
<addr>BORO' ROAD CHAPEL(BAPTIST)</addr>
<addr><i>St. George's National &amp; Parochial Schools</i></addr>
<addr>84 Chenery Hen. Jun. coal merchant</addr>
<addr>85 Moss Thomas Arthur, hat tip stamper in gold</addr>
<addr>86 Miller William, linendraper</addr>
<xst>here the Railway crosses</xst>
<xst>here is Southwark bridge road</xst>
<addr>88 Burdett John, beer retailer</addr>
<addr>90 Wingham Thomas, appraiser</addr>
<addr>92 Wilson George, surgeon</addr>
<addr>93 Hill George Rowland</addr>
<addr>96 &amp; 97 Putney Saml.timber merch</addr>
<addr>101 Maychell Samuel, shoemaker</addr>
<addr>102, 33 &amp; 34 Biggs John, gas enginr</addr>
<xst>here is Lancaster street</xst>
<addr>BRITISH &amp; FOREIGN SCHOOL
SOC. (Central Establishment),
Joseph G. Barclay, treasurer
Alfred Bourne, B.A. sec
Samuel Bradford, accountant</addr>
<addr><i>Normal Coll. for Training Mastrs</i>.
J. C. Curtis, B.A. principal
Alfred Fish Smith, B.A. vice. principal
Edwin Barkley, B.A. master
George Collins, normal mstr
John R.Dicksee,drawng.mstr</addr>
<addr><i>Normal College for Training Mistresses</i>,
Alfred Bourne, B.A. principl
Mrs. Wood, matron
Mrs. Francis Steele, senior mistress
<i>Model Schools</i>,
George Collins, master</addr>
<addr>104 <i>Globe</i>, Edwin Beck</addr>
<addr>105 Adamson William, bootmaker</addr>
<addr>106 Ibbotson Thomas, pork butchr</addr>
<addr>107 Schweim Christian, hairdresser</addr>
<addr>108 Tanner Edward, coal dealer</addr>
<xst>here are Kell st. &amp; Market st.</xst>
<addr>109 Terry J. &amp; Son, timber merchs</addr>
<addr>ST. GEORGE'S (PRESBYTERIAN) CHURCH</addr>
<xst>here is Mansfield street</xst>
<addr>114 Harris John, portable chair ma</addr>
<addr>115 Wood William, coffee rooms &amp;C</addr>
<addr>116 Farrington Sl. marine store dlr</addr>
<addr>117 Ketteridge Arthur, stationer</addr>
<addr>118 Oldroyd John, corn dealer</addr>
<addr>119 Uden John, dairy</addr>
</street>
