<street>
<head>Botolph lane (E.C.) (CITY),</head><head2>111 <i>Lower Thames st. &amp;</i> 14 <i>Eastcheap</i>.</head2>
<map>MAP O9, O10. </map>
<addr>2 <i>Vintners' Porters' Office</i></addr>
<addr>3 Domeier &amp; Co. merchants</addr>
<addr>4 Marshall William&amp; Co. merchants</addr>
<addr>Bridger Reginald, solicitor</addr>
<addr><i>London Patent Felt Co</i>. William Marshall, man</addr>
<addr>4 &amp; 5 Davis &amp; Littlewood, wine mrs</addr>
<addr>5 Roberts &amp; Son, cork mers. &amp; ma</addr>
<addr>6 Jones Griffith, tailor</addr>
<addr>Holland Edwin, provision dealer</addr>
<addr>8 Graham &amp; Co. fruit importers</addr>
<addr>8 Gallagher, Nelson &amp; Co. foreign fruit merchants</addr>
<xst>here is George lane</xst>
<addr>ST. GEORGE &amp; ST. BOTOLPH CHURCH</addr>
<addr>9 to15&amp;32 Keeling&amp; Hunt,fruit brks</addr>
<addr>10 Baylis R. &amp; J. fruit merchants</addr>
<addr>20 &amp; 47 Hanson Samuel &amp; Son, Evison &amp; Barter, foreign fruit importers</addr>
<addr>21 Fisher Rd. Meredith, coffee rms</addr>
<addr>22 &amp; 23 Plumbridge &amp; Son, orange merchants</addr>
<addr>24 Clark John T. fish salesman</addr>
<addr>Barrow Henry, fish salesman</addr>
<addr>Harmer John, oyster merchant</addr>
<addr>Thompson Bros. fish salesmen</addr>
<addr>Ede Frederick, fish salesman</addr>
<addr>Batger L. W. &amp; Co. merchants</addr>
<addr>26 Christie George, printer</addr>
<addr>27 <i>White Hart</i>, Mrs. Sarah Linfield</addr>
<addr>28 Brice Brothers, oyster salesmen</addr>
<addr>29 Balkwill &amp; Blackman, fruit mers</addr>
<addr>29 &amp; 30 Pinkerton Mark, merchant</addr>
<addr>Dixon George, printer</addr>
<addr>Feaks &amp; Masters, carmen</addr>
<addr>Glyn John, &amp; Co. fruit merchnts</addr>
<addr>NathanLionel&amp; Co.cigar imprtrs</addr>
<addr>30 &frac12; Hill, John, wine merchant</addr>
<addr>31 &amp; 35 Knill &amp; Grant, fruit brokrs</addr>
<addr>32 Fenn &amp; Ellis, wholesale grocers</addr>
<addr>32&amp;9to15 Keeling &amp; Hunt, fruit bkrs</addr>
<addr>32 <i>Billingsgate Ward School</i>Boosey Wm. Hy. &amp; Co. engravers</addr>
<addr>35 &amp; 31 Knill &amp; Grant, fruit brokrs</addr>
<addr>38 Johnston &amp; Son, fruit merchnts</addr>
<addr>39 Meek Charles &amp; Sons, plumbers</addr>
<addr>Nelson Ths. &amp;Son, ship&amp;ins.brkrs</addr>
<addr>40 Ellis William, carpenter</addr>
<xst>here is Botolph alley</xst>
<addr>41 Trimmer&amp; Son,commercial agnts</addr>
<addr>42 BowerJohn&amp;Co. fruit merchants</addr>
<addr>43 <i>Clerical, Medical &amp; General Tea Association</i> H. Parkinson, manager</addr>
<addr>Parkinson Henry, merchant</addr>
<addr>45 Shackleton &amp; Co. eastind. merch</addr>
<addr>47 &amp; 20 Hanson Samuel &amp; Son,
Evison &amp; Barter, whols. grocers</addr>
<xst>here is Weighhouse yard</xst>
</street>
