<street>
<head>Brecknock road (N.),</head><head2><i>from Camden road to Junction rd</i>.</head2><map>MAP J3, K3, K4.</map>
<side>WEST SIDE.</side>
<addr>1 Adams John, cheesemonger</addr>
<addr>3 Chappell Chas. fancy repository</addr>
<addr>5 Brown Joseph &amp; Co. dyers</addr>
<addr>7 Klosz &amp; Co. grocers</addr>
<addr>9 Sargent William, hairdresser</addr>
<addr>11 &amp; 13 Ball &amp; Wickes, builders</addr>
<addr>York Fredk. H. livery stables (Manville yard)</addr>
<addr>17 Waldby Thomas, cabinet maker</addr>
<addr>19 Johnson Charles, toy warehouse</addr>
<addr>21 Saunders Wm. china &amp; glass wa</addr>
<addr>23 Thorpe Charles, fruiterer</addr>
<addr>25 Morgan David, pharm. chemist</addr>
<xst>here is James street</xst>
<addr>27 Davies Thos. &amp; Co. linendrapers</addr>
<addr>29 Greensted Henry, grocer</addr>
<addr>31 Cudby Edward Joseph, fishmngr</addr>
<addr>33 Lee James, cheesmonger</addr>
<addr>47 Clark Mrs</addr>
<addr>49 Shillitoe Mrs</addr>
<addr>51 Allen Richard, house decorator</addr>
<addr>53 Pugh Richard</addr>
<xst>here is Leighton road</xst>
<addr>55 Stow Mrs</addr>
<addr>57 Willis Michael</addr>
<addr>59 Crisp George</addr>
<addr>61 Holdgate Edward</addr>
<addr>63 Ramsley Mrs</addr>
<addr>67 Foale Mrs</addr>
<addr>69 Waller George</addr>
<addr>71 Coleman EverardHome, F.R.A.S., F.R.G.S</addr>
<addr>73 Dixon William</addr>
<addr>75 Warren John</addr>
<addr>77 Brown Thomas</addr>
<addr>79 Sanderson Mrs</addr>
<addr>81 Procter John</addr>
<addr>83 Flint Fenner Ludd</addr>
<addr>85 Valogne Charles</addr>
<addr>87 Clark Charles</addr>
<addr>89 Campbell Malcolm</addr>
<addr>91 Marler Henry William</addr>
<addr>93 Philpot James</addr>
<addr>95 Clark Samuel James</addr>
<addr>97 Flexman Mrs</addr>
<addr>99 Freeman Josiah, baker</addr>
<xst>here is Leighton grove</xst>
<addr>101 <i>Leighton Arms</i>, Edmund Francis Chown</addr>
<addr>103 Stevens Joseph</addr>
<addr>105 Drew Miss Maria, school</addr>
<addr>107 Oakman Charles</addr>
<addr>109 Dowse Mrs</addr>
<addr>111 Palethorpe Mrs</addr>
<addr>113 Elmer Obadiah</addr>
<addr>115 Burroughes William Henry</addr>
<addr>117 Thorne Thomas</addr>
<addr>119 Wallis Capt. Alexander B</addr>
<addr>121 Vine William</addr>
<addr>Vine William John</addr>
<addr>123 Button William</addr>
<addr>125 Holland Hubert Charles</addr>
<addr>127 Cluff John Warren</addr>
<addr>129 Rutter John</addr>
<addr>131 Anderson John</addr>
<addr>133 Griffith Capt. George</addr>
<addr>135 Freeman Mrs</addr>
<addr>137 Higgins Edward Jones</addr>
<xst>here are Montpelier &amp; Ospringe roads</xst>
<addr>139 Gain Frederick</addr>
<addr>141 Owen William</addr>
<addr>143 Keulemans Adrian</addr>
<addr>145 Smith William</addr>
<addr>147 Race William</addr>
<addr>149 Hadley Arthur</addr>
<addr>151 Harper Mrs</addr>
<addr>153 Catchpole Edward</addr>
<addr>155 Wilsden Mrs</addr>
<addr>157 Venables Arthur</addr>
<addr>159 Tipper Edward</addr>
<addr>161 Birks Harry William, F.R.G.S</addr>
<side>EAST SIDE.</side>
<addr>2 Barrett Harry, watchmaker</addr>
<addr>4 Bungey Frederick John, fruiterer</addr>
<addr>6 Hall Charles, tobacconist</addr>
<addr>8 Tyrrell John, linendraper</addr>
<addr>10 Webb Edward, ironmonger</addr>
<addr>12 Hanes William, fishmonger</addr>
<addr>14 Bickerton Adrian Harbut, grocer</addr>
<addr>16 Faber Philip, baker</addr>
<addr>18 Attfield William Henry, butcher</addr>
<addr>20 Eastman Robt.&amp;Sons,carpenters</addr>
<addr>22 Churchill Mrs.My.Ann. fancyrep</addr>
<addr>24 Tyson Joseph James, boot maker</addr>
<addr>26 Hitchcock Henry, corndealer</addr>
<addr>28 Bridger Edmund, dairyman</addr>
<addr>30 Glackner Charles, oilman</addr>
<addr>32 Trimmell Mrs. Sarah, milliner</addr>
<addr>34 Small William, plumber</addr>
<addr>36 Reeve Thomas</addr>
<addr>38 Timms &amp; Son, photographers</addr>
<addr>40 Endle Charles John</addr>
<addr>42 Pinnock Miss</addr>
<addr>44 Foskett Hy. gold &amp; silver chaser</addr>
<addr>46 Cudby George Thomas</addr>
<addr>48 Dalman Mrs</addr>
<addr>50 Skidmore &amp; Son, house agents</addr>
<addr>52 Lang Edwin</addr>
<addr>54 Grossmith Robert</addr>
<addr>56 Taylor Benjamin</addr>
<addr>58 Harding Edward</addr>
<addr>60 Briggs David</addr>
<addr>62 Reeve Mrs</addr>
<addr>Woolley Miss</addr>
<addr>64 Seymour Capt. George Frederick</addr>
<addr>66 Dowdall Mrs</addr>
<xst>here is Hilldrop crescent</xst>
<addr>70 Spicer Frederick</addr>
<addr>72 Bannister Robert Hope</addr>
<addr>74 Walenn William Henry, F.I.C., F.C.S. civil engineer</addr>
<addr>76 Green Edward</addr>
<addr>78 Baker Frederick George</addr>
<addr>80 Townshend Edward, accountant</addr>
<addr>82 Pyne Thomas</addr>
<addr>84 Gilbert William</addr>
<addr>86 Murfey Mrs</addr>
<addr>88 Bremner Alexander</addr>
<addr>90 Taylor William</addr>
<addr>92 Lomas William</addr>
<addr>94 Painter William</addr>
<addr>96 Hamilton Mrs</addr>
<xst>here is Hilldrop road</xst>
<addr>100 Braine Thomas</addr>
<addr>102 Grattan Mrs</addr>
<addr>104 Wellan/?/d Mrs</addr>
<addr>106 Wolff Henry Adolphus</addr>
<addr>108 Tarry Mrs</addr>
<addr>110 Davies Robert Henry</addr>
<addr>112 Fincham Miss</addr>
<xst>here is Tufnell park west</xst>
<addr>120 Nodes Mrs</addr>
<addr>122 Glover Mrs</addr>
<addr>124 Butcher James Burrows</addr>
<addr>126 Reading Richard</addr>
<addr>128 Appleton G. Webb</addr>
<addr>130 Gurney Thomas Benjamin</addr>
<addr>132 Robinson Mrs</addr>
<addr>134 Powell Philip John</addr>
<addr>136 Weatherbee George</addr>
<addr>138 Kemp Francis John</addr>
<addr>140 Jones John</addr>
<addr>142 Benedict George</addr>
<addr>144 Hart Henry</addr>
<addr>146 Batley Mrs</addr>
<addr>148 Wells Benjamin</addr>
<addr>150 Mullens John Langford</addr>
<addr>152 Kemp Miss</addr>
<addr>154 Tickle Japheth</addr>
<addr>156 Cocke Alfred</addr>
<addr>158 Berrell William</addr>
<addr>160 Arclus George</addr>
<addr>162 Shaw Mrs</addr>
<addr>164 Newstead Mrs</addr>
<addr>Newstead Edward Flashman</addr>
<addr>166 Mundy Stephen</addr>
<addr>168 Maillard Thomas De Charms</addr>
<addr>170 Pugh Mrs</addr>
<addr>Pugh Edward</addr>
</street>
