<street>
<head>Barge yd. 19,</head><head2><i>Bucklersbury</i> (<b>E.C</b>) (CITY).</head2><map>MAP N9.</map>
<addr>5 Gammon Charles, solicitor</addr>
<addr>Navin &amp; Co. east india merchnts
MacGavin &amp; Co.wine merchants</addr>
<addr>Lafosse Louis &amp; Co.wine growers</addr>
<addr>Robinson Edward L. G. solicitor</addr>
<addr>Savory Henry, merchant</addr>
<addr>Peel Jonathan, merchant
Macfarlan John Fletcher &amp; Co. manufacturing chemists
Hunt &amp; Sacr&eacute;, engineers
Cartwright Richd. law stationer</addr>
<addr>Thorpe Samuel, printer
Cammell Charles &amp; Co. Limited, steel &amp; file manufacturers</addr>
<addr>6 Turner William &amp; Co. packers</addr>
<addr>Boutland Charles &amp; Hen.carriers
Boutland William, corn dealer</addr>
<addr>3 Newson William &amp; Co. indian condiment manufacturers</addr>
<addr>2 Forbes Chs.Carey,australian mer</addr>
<addr>Hastwell, Forbes &amp; Co. wine &amp; spirit merchants
Clicquot Henri,champgne.growr</addr>
<addr>Butterfield &amp; Co. oil merchants</addr>
</street>
