<street>
<head>Billiter sq.</head><head2>11 &amp; 12 <i>Billiter 
st</i>. (<b>E.C.</b>). (CITY).</head2><map>MAP O9.</map>
<addr>1 Croxson F. &amp; Co. dining rooms</addr>
<addr>2 Bell,Brandenburg&amp; Co.e.ind.mrs</addr>
<addr>2 Sacs &amp; H&ouml;hchheimer, wine mers</addr>
<addr>Dawson Bros, agents Dawson Brothers, ship&amp;ins.agnts</addr>
<addr>Neave Richard &amp; Thos. merchnts</addr>
<addr>Robertson James Roderick</addr>
<addr>FenestreJosph.french gds.imprtr</addr>
<addr>Nuwendam &amp; Klu&yuml;skens, wine
importers, J. Fenestre, agt</addr>
<addr>3 Hopcraft&amp; Broadwater,shipping agents</addr>
<addr>Moore &amp; Manby, iron merchants</addr>
<addr>4 Barnard Clement, civ. engineer</addr>
<addr>Anderson Thomas, merchant</addr>
<addr>Curtis Bros. wine&amp;spirit merchts</addr>
<addr>Stubbs (Robert) &amp; Co. whole 
sale fancy stationers</addr>
<addr>ScholeyJoshuaWm. tobacco brkr</addr>
<addr>Yates G. B. &amp; Son, merchants &amp;c</addr>
<addr>YatesHenryGeo.insurance agent</addr>
<addr>Seaman EdwardCleveland,solctr</addr>
<addr><i>English &amp; Foreign Shipowners' Protection Association</i>, Henry Roth, sec</addr>
<addr>Mertens&amp;Co.(Constant)ship.agts</addr>
<addr>Jacquesson&amp; Fils,chmpgn.grwrs Mertens &amp; Co. agents</addr>
<addr>Sage Isidore Le, wine agent</addr>
<addr>6 Thomson Jas.&amp; Co.ship&amp;ins.bros</addr>
<addr>Hammond Chas. westindia mer</addr>
<addr>Lidgett John &amp; Sons, merchants</addr>
<addr>7 Dubois Ernest, wine agent</addr>
<addr>Dubois Frer&amp; Cagnion,shippers</addr>
<addr>8 Clagett,Brachi&amp;Co.tobacco brkrs</addr>
<addr>Dawson Charles C. shipowner</addr>
<addr>Gouger Alfd. &amp; Co. east ind. Mers</addr>
<addr>De Putron &amp; Rooth, merchants</addr>
<addr>9 Bremner A. B.&amp;Co.tobacco brkrs
<i>West India Planters' &amp; Merchants'</i> (<i>Standing Committee of</i>), J. L. Ohlson, sec
Williams, Brown &amp; Elmslie, wharfingers
Thomson P. J. &amp; Co. merchants</addr>
<addr>10 Druce, Sons &amp; Jackson, solicitors</addr>
<addr>Pritchard Henry, solicitor</addr>
<addr>11 Fuller, Horsey, Sons&amp;Co.auctinrs</addr>
<addr>R&ouml;sing Bros. &amp; Co. merchants</addr>
<addr>11 ShadboltGeo.&amp;Son,mhgny. brkrs</addr>
<addr>BannerBros. &amp;Co.mers.&amp;shipown</addr>
<addr>Bassermann Fredk. Louis, mer</addr>
<addr>Haslehurst Edmd.&amp; Co.ship bros</addr>
<addr><i>Importers' &amp; Consumers' Tea 
Association</i>,
Hy. Geo. Hollingworth, sec
Quintas Seoane, Zaro &amp; Co. mers</addr>
</street>
