<street>
<head>Bury st.</head><head2><i>James's</i>(<b>S.W.</b>), 72 &amp; 73 <i>Jermyn street to</i>12 &amp; 13 <i>King st</i>.</head2><map>MAP J10.</map>
<addr>2 Challis Miss Edith, lodginghouse</addr>
<addr>Cook Henry &amp; Co. bootmakers</addr>
<addr>3 Barker Thomas, biscuit baker</addr>
<addr>4 Starke M. &amp; Son, fruiterers</addr>
<addr>5 Southey Wm. Edwd. lodging ho</addr>
<addr>Barttelot Col. Sir Walter Barttelot, bart. M.P</addr>
<addr>Grant Sir Archibald, bart</addr>
<addr>Churchill Lord</addr>
<addr>6 Sommerlat Mrs</addr>
<addr>7 Greenhill Geo&amp; Co.wax chandlrs</addr>
<addr>Shipwash &amp; Co. mineral water wa</addr>
<addr>Turpin William, private hotel</addr>
<addr>8 Jones &amp; Yarrell, newspaper agts</addr>
<addr>Poulter Reginld.Cliffrd.news agt</addr>
<addr>9 Cullen &amp; Brand, butchers</addr>
<xst>here is Ryder street</xst>
<addr>10 &amp; 11, <i>Pearce' s hotel</i>, Alfd.Richards</addr>
<addr>Beaumont Walter</addr>
<addr>Mosley Ernald</addr>
<addr>Osborne Lord D'Arcy</addr>
<addr>12 <i>Couriers' Soc</i>.Wm. Dennett, sec</addr>
<addr>13 Bradley Mrs. Elizbth. lodging ho</addr>
<addr>14 <i>George</i>, Henry Couchman</addr>
<addr>15 Balls Thomas, lodging house</addr>
<addr>16 Welch Wyndham, lodging house</addr>
<addr>17 Menday William, lodging house</addr>
<addr>19 Bailey William, lodging house</addr>
<addr>20 Boyazoglu Nicolas</addr>
<addr>Balli Alexandre</addr>
<addr>Kummerer Rudolph</addr>
<addr>Stavenhagen Edward</addr>
<addr>Wild Charles Thompson</addr>
<xst>here is Jermyn street</xst>
<addr>25 Lodge George, lodging house</addr>
<addr>26 Oldham Mrs. Ann, lodging house</addr>
<addr>Ibbotson Rev. Charles</addr>
<addr>Kettlewell William Wildman</addr>
<addr>White Miss</addr>
<addr>26A, Peterson Edward W. I. &amp; Wm. C. R. solicitors</addr>
<addr>27 Rutter Misses Mary &amp; Sarah, lodging house</addr>
<addr>Evans Fleming Patrick</addr>
<addr>Glover Capt. Sir John Hawley, R.N., G.C.M.G</addr>
<addr>Glover Rev. Fredk.Rbt.Augustus</addr>
<addr>Hawkins Christopher Henry</addr>
<addr>Prescott Col. Cyril Jackson</addr>
<addr>Ramsay William</addr>
<addr>28 Finch Col. Hon. Daniel</addr>
<addr>Spaun Baron Hermann</addr>
<addr>29 Fisher James, lodging house</addr>
<addr>30 Measday Thomas, lodging house</addr>
<xst>here is Ryder street</xst>
<addr>36 Rawlings Wm. lodging house</addr>
<addr>37 Faithfull Mrs. Olive, lodging ho</addr>
<addr>38 Smith William, private hotel</addr>
</street>
